phew/__init__.py
phew/Annuity.py
phew/Cola.py
phew/Expenses.py
phew/Interest_rates/__init__.py
phew/Interest_rates/formulae.py
phew/Interest_rates/models.py
phew/Loss_given_delay.py
phew/Premium.py
phew/Time_value.py
phew-1.2.0.dist-info/METADATA
phew-1.2.0.dist-info/WHEEL
phew-1.2.0.dist-info/RECORD
