Metadata-Version: 2.1
Name: phew
Version: 1.2.0
Summary: a library housing basic mathematical and statistical formulae used in insurance.
License: MIT
Keywords: social,insurance,finance,travel,trip,delay,social travel insurance,trip delay coverage
Author: Precious Nliwasa
Author-email: preciousnliwasa8@gmail.com
Requires-Python: >=3.9,<4.0
Classifier: License :: OSI Approved :: MIT License
Classifier: Programming Language :: Python :: 3
Classifier: Programming Language :: Python :: 3.9
Classifier: Programming Language :: Python :: 3.10
Classifier: Programming Language :: Python :: 3.11
Classifier: Programming Language :: Python :: 3.12
Requires-Dist: statsmodels (>=0.14.1,<0.15.0)
Project-URL: Documentation, https://preciousnliwasa.github.io/phew_docs/userguide/
